compare_folders/__init__.py
compare_folders/__main__.py
compare_folders-3.1.0.dist-info/METADATA
compare_folders-3.1.0.dist-info/WHEEL
compare_folders-3.1.0.dist-info/entry_points.txt
compare_folders-3.1.0.dist-info/RECORD
