Metadata-Version: 2.4
Name: compare-folders
Version: 3.1.0
Summary: Tool to compare two folders
Author: skarfie123
Author-email: rahulpai@rocketmail.com
Requires-Python: >=3.10
Classifier: Programming Language :: Python :: 3
Classifier: Programming Language :: Python :: 3.10
Classifier: Programming Language :: Python :: 3.11
Classifier: Programming Language :: Python :: 3.12
Classifier: Programming Language :: Python :: 3.13
Classifier: Programming Language :: Python :: 3.14
Requires-Dist: typer (>=0.17.0,<0.18.0)
Project-URL: Repository, https://github.com/skarfie123/compare-folders
